rues/Individual.py
rues/Population.py
rues/__init__.py
rues/crossover_algorithms/__init__.py
rues/crossover_algorithms/blend_crossover.py
rues/crossover_algorithms/k_point_crossover.py
rues/genetic_algo.py
rues/model.py
rues/mutation_algorithms/__init__.py
rues/mutation_algorithms/uniform_mutator.py
rues/reinsertion_algorithms/__init__.py
rues/reinsertion_algorithms/age_model.py
rues/reinsertion_algorithms/fittest_model.py
rues/selection_algorithms/__init__.py
rues/selection_algorithms/create_random_pairs.py
rues/selection_algorithms/roulette_wheel.py
rues/selection_algorithms/stochastic_US.py
rues/selection_algorithms/tournament.py
rues/utils/__init__.py
rues/utils/multiprocessing/__init__.py
rues/utils/multiprocessing/handler.py
rues/utils/multiprocessing/worker.py
rues/utils/sort_population.py
rues-0.1.1.3.dist-info/LICENSE
rues-0.1.1.3.dist-info/WHEEL
rues-0.1.1.3.dist-info/METADATA
rues-0.1.1.3.dist-info/RECORD
