Metadata-Version: 2.1
Name: rues
Version: 0.1.1.3
Summary: rues - genetic algorithms in python
Author: Kamuish
Author-email: andremiguel952@gmail.com
Requires-Python: >=3.8,<4.0
Classifier: Programming Language :: Python :: 3
Classifier: Programming Language :: Python :: 3.8
Requires-Dist: corner (>=2.0.1,<3.0.0)
Requires-Dist: matplotlib (>=3.1.3,<4.0.0)
Requires-Dist: numpy (>=1.18.1,<2.0.0)
Requires-Dist: scipy (>=1.4.1,<2.0.0)
Requires-Dist: sphinx (>=3.1.0,<4.0.0)
Requires-Dist: sphinxcontrib-bibtex (>=1.0.0,<2.0.0)
